litepolis_router_database_sqlite/Comments.py
litepolis_router_database_sqlite/Conversations.py
litepolis_router_database_sqlite/Users.py
litepolis_router_database_sqlite/__init__.py
litepolis_router_database_sqlite/core.py
litepolis_router_database_sqlite/utils.py
litepolis_router_database_sqlite-0.0.1.dist-info/LICENSE
litepolis_router_database_sqlite-0.0.1.dist-info/METADATA
litepolis_router_database_sqlite-0.0.1.dist-info/WHEEL
litepolis_router_database_sqlite-0.0.1.dist-info/top_level.txt
litepolis_router_database_sqlite-0.0.1.dist-info/RECORD
