Metadata-Version: 2.2
Name: litepolis-router-database-sqlite
Version: 0.0.1
Summary: The sqlite database module for LitePolis
Home-page: https://github.com/NewJerseyStyle/LitePolis-router-database-example
Author: David
License: MIT License
License-File: LICENSE
Requires-Dist: fastapi
Requires-Dist: sqlmodel
Dynamic: author
Dynamic: description
Dynamic: description-content-type
Dynamic: home-page
Dynamic: license
Dynamic: requires-dist
Dynamic: summary
